py_markdown_table/__init__.py
py_markdown_table/markdown_table.py
py_markdown_table/utils.py
py_markdown_table-1.2.0.dist-info/LICENSE
py_markdown_table-1.2.0.dist-info/METADATA
py_markdown_table-1.2.0.dist-info/WHEEL
py_markdown_table-1.2.0.dist-info/RECORD
