Metadata-Version: 2.1
Name: py-markdown-table
Version: 1.2.0
Summary: Package that generates markdown tables from a list of dicts
Home-page: https://github.com/hvalev/py-markdown-table
License: MIT
Author: hvalev
Requires-Python: >=3.8,<4.0
Classifier: License :: OSI Approved :: MIT License
Classifier: Operating System :: OS Independent
Classifier: Programming Language :: Python :: 3
Classifier: Programming Language :: Python :: 3.8
Classifier: Programming Language :: Python :: 3.9
Classifier: Programming Language :: Python :: 3.10
Classifier: Programming Language :: Python :: 3.11
Classifier: Programming Language :: Python :: 3.12
Classifier: Programming Language :: Python :: 3.13
